scmap.py
scmap-0.1.0.dist-info/LICENSE
scmap-0.1.0.dist-info/METADATA
scmap-0.1.0.dist-info/WHEEL
scmap-0.1.0.dist-info/top_level.txt
scmap-0.1.0.dist-info/RECORD
