Metadata-Version: 2.1
Name: scmap
Version: 0.1.0
Summary: Assigns rgb colors to points on sphere.
Home-page: https://github.com/vedranaa/sphere-colormap
Author: Vedrana Andersen Dahl
Author-email: vand@dtu.dk
License: lgpl-2.1
Platform: UNKNOWN
License-File: LICENSE
